Workbook

Sheet 🔒 内部智能核价台(业务员专享)
B2: ⚡ 2026 外贸智能核价与防泄露控制台 · Kelvin 极客版
B3: 【内部保密 · 业务员专享】本表内置动态公式与利润红线防御机制。本表所有成本底价与公式严禁直接发给买家！对外报价请直接复制下一页【对外商业报价单】。
B5: 🌐 宏观汇率与港杂设定 | F5: 🛡️ 利润安全红线预警 | J5: 💡 技术老友 Kelvin 的独家防翻车提示
B6: 实时基准汇率: | C6: 7.2 | D6: 安全核算汇率: | E6: =C6-0.12 | F6: 最低毛利底线: | G6: 0.18 | H6: 单票港杂费基准(RMB): | I6: 1800 | J6: 安全汇率已自动扣减 0.12 安全垫，锁定汇率波动风险；毛利低于 18% 状态栏自动警报！
B8: SKU / 产品型号 | C8: 产品英文描述 | D8: 工厂底价 (¥) | E8: 选配工艺加价 (¥) | F8: 外箱包装费 (¥) | G8: 单箱装量(PCS) | H8: 单件港杂分摊(¥) | I8: 单件综合成本(¥) | J8: 目标毛利率 | K8: 出厂人民币单价 | L8: 核算汇率 | M8: FOB美元单价 ($) | N8: 单件利润 ($) | O8: 利润红线状态
B9: ST-2026-PRO | C9: Ergonomic Laptop Stand (Alu) | D9: 45 | E9: 3.5 | F9: 8 | G9: 10 | H9: 1.2 | I9: =D9+E9+(F9/G9)+H9 | J9: 0.28 | K9: =I9/(1-J9) | L9: =$E$6 | M9: =ROUND(K9/L9, 2) | N9: =ROUND((K9-I9)/L9, 2) | O9: =IF(J9<$G$6, "🚨 警报:低于红线", IF(J9>=0.25, "✅ 健康高毛利", "⚠️ 勉强保本"))
B10: ST-2026-LITE | C10: Foldable Metal Phone Holder | D10: 16.5 | E10: 1 | F10: 4.5 | G10: 20 | H10: 0.6 | I10: =D10+E10+(F10/G10)+H10 | J10: 0.25 | K10: =I10/(1-J10) | L10: =$E$6 | M10: =ROUND(K10/L10, 2) | N10: =ROUND((K10-I10)/L10, 2) | O10: =IF(J10<$G$6, "🚨 警报:低于红线", IF(J10>=0.25, "✅ 健康高毛利", "⚠️ 勉强保本"))
B11: ERG-ARM-V2 | C11: Heavy Duty Dual Monitor Arm | D11: 125 | E11: 8 | F11: 18 | G11: 2 | H11: 3.5 | I11: =D11+E11+(F11/G11)+H11 | J11: 0.32 | K11: =I11/(1-J11) | L11: =$E$6 | M11: =ROUND(K11/L11, 2) | N11: =ROUND((K11-I11)/L11, 2) | O11: =IF(J11<$G$6, "🚨 警报:低于红线", IF(J11>=0.25, "✅ 健康高毛利", "⚠️ 勉强保本"))
B12: AL-BASE-99 | C12: Die-cast Aluminum Base Mount | D12: 38 | E12: 2 | F12: 6 | G12: 8 | H12: 1 | I12: =D12+E12+(F12/G12)+H12 | J12: 0.15 | K12: =I12/(1-J12) | L12: =$E$6 | M12: =ROUND(K12/L12, 2) | N12: =ROUND((K12-I12)/L12, 2) | O12: =IF(J12<$G$6, "🚨 警报:低于红线", IF(J12>=0.25, "✅ 健康高毛利", "⚠️ 勉强保本"))
B13: HD-ARM-08 | C13: Gas Spring Articulating Arm | D13: 82 | E13: 5 | F13: 12 | G13: 4 | H13: 2.2 | I13: =D13+E13+(F13/G13)+H13 | J13: 0.22 | K13: =I13/(1-J13) | L13: =$E$6 | M13: =ROUND(K13/L13, 2) | N13: =ROUND((K13-I13)/L13, 2) | O13: =IF(J13<$G$6, "🚨 警报:低于红线", IF(J13>=0.25, "✅ 健康高毛利", "⚠️ 勉强保本"))
B14: CUSTOM-SPEC-01 | C14: OEM Matte Black Desk Converter | D14: 210 | E14: 15 | F14: 35 | G14: 1 | H14: 8 | I14: =D14+E14+(F14/G14)+H14 | J14: 0.12 | K14: =I14/(1-J14) | L14: =$E$6 | M14: =ROUND(K14/L14, 2) | N14: =ROUND((K14-I14)/L14, 2) | O14: =IF(J14<$G$6, "🚨 警报:低于红线", IF(J14>=0.25, "✅ 健康高毛利", "⚠️ 勉强保本"))
B16: 📦 智能柜型装载与 CBM 体积自动速算器 (输入外箱尺寸，秒出 20GP / 40GP / 40HQ 柜量)
B17: SKU / 型号 | C17: 箱长 L (cm) | D17: 箱宽 W (cm) | E17: 箱高 H (cm) | F17: 单箱体积 (CBM) | G17: 单箱毛重 (KG) | H17: 每箱装量 | I17: 20GP装箱数(28m³) | J17: 20GP总件数(PCS) | K17: 40GP装箱数(58m³) | L17: 40GP总件数(PCS) | M17: 40HQ装箱数(68m³) | N17: 40HQ总件数(PCS) | O17: 装柜空间利用评估
B18: ST-2026-PRO | C18: 45 | D18: 32 | E18: 28 | F18: =ROUND(C18*D18*E18/1000000, 4) | G18: 12.5 | H18: 10 | I18: =INT(28/F18) | J18: =I18*H18 | K18: =INT(58/F18) | L18: =K18*H18 | M18: =INT(68/F18) | N18: =M18*H18 | O18: 🟢 满柜出货推荐
B19: ST-2026-LITE | C19: 30 | D19: 25 | E19: 20 | F19: =ROUND(C19*D19*E19/1000000, 4) | G19: 8 | H19: 20 | I19: =INT(28/F19) | J19: =I19*H19 | K19: =INT(58/F19) | L19: =K19*H19 | M19: =INT(68/F19) | N19: =M19*H19 | O19: 🟢 满柜出货推荐
B20: ERG-ARM-V2 | C20: 65 | D20: 42 | E20: 35 | F20: =ROUND(C20*D20*E20/1000000, 4) | G20: 18.2 | H20: 2 | I20: =INT(28/F20) | J20: =I20*H20 | K20: =INT(58/F20) | L20: =K20*H20 | M20: =INT(68/F20) | N20: =M20*H20 | O20: 🟢 满柜出货推荐
B24: 💡 技术老友 Kelvin 的心里话： 亲爱的外贸朋友，如果你还在每天手动算几十个复杂 SKU、或者买家总发长篇英文邮件询价让你头大，试试我为你写好的免费 AI 自动审单引擎 KelvinFlow (https://kelvinflow.com)。复制邮件 10 秒全自动拆解 SKU、匹配底价并生成纯英文正式 PDF 报价单！小红书群友可在官方交流群内随时提需求，我来为你免审开通体验！欢迎在官方粉丝群内交流反馈

Sheet 📄 对外商业报价单(纯净导出)
B2: GLOBAL EXPORT FORMAL QUOTATION
B3: Commercial Offer & Export Terms · Valid for 15 Days from Issue Date
B5: Supplier: ACME Hardware & Ergonomics Co., Ltd. | F5: Quote Ref: QT-2026-EXP-3096
B6: Port of Loading: Shenzhen / Guangzhou Port, China | F6: Trade Term: FOB Shenzhen (Incoterms 2020)
B7: Currency: United States Dollar (USD) | F7: Payment Term: 30% T/T Deposit, 70% Balance Before Shipment
B9: Item | C9: Model No. | D9: Description & Detailed Specs | E9: Unit | F9: MOQ | G9: FOB Price (USD) | H9: Lead Time
B10: 1 | C10: ='🔒 内部智能核价台(业务员专享)'!B9 | D10: ='🔒 内部智能核价台(业务员专享)'!C9 | E10: PCS | F10: 500 | G10: ='🔒 内部智能核价台(业务员专享)'!M9 | H10: 15-20 Days
B11: 2 | C11: ='🔒 内部智能核价台(业务员专享)'!B10 | D11: ='🔒 内部智能核价台(业务员专享)'!C10 | E11: PCS | F11: 500 | G11: ='🔒 内部智能核价台(业务员专享)'!M10 | H11: 15-20 Days
B12: 3 | C12: ='🔒 内部智能核价台(业务员专享)'!B11 | D12: ='🔒 内部智能核价台(业务员专享)'!C11 | E12: PCS | F12: 500 | G12: ='🔒 内部智能核价台(业务员专享)'!M11 | H12: 15-20 Days
B13: 4 | C13: ='🔒 内部智能核价台(业务员专享)'!B12 | D13: ='🔒 内部智能核价台(业务员专享)'!C12 | E13: PCS | F13: 500 | G13: ='🔒 内部智能核价台(业务员专享)'!M12 | H13: 15-20 Days
B14: 5 | C14: ='🔒 内部智能核价台(业务员专享)'!B13 | D14: ='🔒 内部智能核价台(业务员专享)'!C13 | E14: PCS | F14: 500 | G14: ='🔒 内部智能核价台(业务员专享)'!M13 | H14: 15-20 Days
B15: 6 | C15: ='🔒 内部智能核价台(业务员专享)'!B14 | D15: ='🔒 内部智能核价台(业务员专享)'!C14 | E15: PCS | F15: 500 | G15: ='🔒 内部智能核价台(业务员专享)'!M14 | H15: 15-20 Days
B17: Remarks & Standard Terms: 1. Quotation based on full carton packing. Customized packaging and branding available upon request. 2. Prices are valid for 15 days due to raw material and international currency fluctuations. 3. Inspection: Standard AQL Level II (Major 1.5, Minor 4.0) before container loading.
