Workbook

Sheet 📌 使用指南与提效神器
B2: 【2026外贸出厂底价表与智能核价模板】使用指南
B3: 💡 本地离线版与线上版 KelvinFlow (https://quote.kelvinflow.com) 采用 100% 相同数据架构。在此填写的全部数据，日后可直接无损上传，零学习成本。
B5: 1. 为什么做这套表？ | C5: 拒绝单品手工反复按计算器！本表专为工贸一体外贸工厂、外贸公司与独立业务员打造。左侧批量录入底价与箱规，右侧全自动联动秒出全量多币种 FOB 美金单价、集装箱装柜量与利润红线防御。
B6: 2. 【⚙️ 全局核算参数】怎么用？ | C6: 在第 2 张工作表设定贵司的内部锁定汇率（如 USD 7.20）、全厂保底毛利（如 15%）、利润防穿底红线（如 8%）与海运进仓港杂平摊（如 0.20 元/件）。在此修改后，全厂全量商品自动秒级联动更新。
B7: 3. 【📦 商品出厂底价库】怎么用？ | C7: 在第 3 张工作表批量录入产品 SKU、出厂底价与包装尺寸。黄色公式区会自动联动倒算出精准 FOB 美金报价、自动算出 20GP/40HQ 可装柜件数；若某品毛利低于红线会自动闪烁警报。
B8: 4. 对外发给买家安全吗？ | C8: 100% 安全！第 4 张工作表【📄 对外纯净批量报价单】专为海外买家设计，工厂出厂底价、内部成本与真实毛利率全部自动脱敏隐藏，可直接打印或导出 PDF 发给海外买家。
B9: 5. 🚀 无缝升级线上版 (SaaS 原生直通) | C9: 本表格式与 KelvinFlow 智能出单引擎 (https://quote.kelvinflow.com) 完全一致！平时直接当离线底价库用；一旦买家发来几十个型号的长篇英文邮件或 PDF 询盘，直接把本表上传到系统，转发邮件，AI 10 秒自动审单对齐底价生成专业英文报价单。小红书官方群友免审开通 7 天深度体验。
B10: 6. 开源与版权说明 | C10: 由大湾区全栈独立开发者 Kelvin (IT佬Kelvin) 荣誉出品，永久免费，纯净无广告，禁止二次倒卖。欢迎在小红书官方粉丝群内交流探讨！

Sheet ⚙️ 全局核算参数 (Config)
A1: 🏢 我司外贸出厂核算控制台 · 全局业务参数配置 (Global Configuration)
A2: 💡 本表由企业掌门人/财务部专管；在此设定的汇率、保底毛利率与业务条款将自动应用于系统全量商品出厂核算。修改后即时全厂生效。
A4: 💵 模块一：结算币种与内部锁定汇率 (Currency & Exchange Rates)
A5: 外币币种 (Target Currency) | B5: 内部锁定汇率 (Rate To RMB) | C5: 币种符号 (Symbol) | D5: 汇率波动预警保护基准 | E5: 适用采购区域 (采购商来源)
A6: USD | B6: 7.2 | C6: $ | D6: ★ 基准主币种 (波动±3%保护) | E6: 北美、东南亚、全球主流外贸结算 (默认主币种)
A7: EUR | B7: 7.85 | C7: € | D7: 基准锁定汇率 (波动±3%保护) | E7: 欧盟及欧洲自由贸易区国家采购商
A8: GBP | B8: 9.1 | C8: £ | D8: 基准锁定汇率 (波动±3%保护) | E8: 英国及英联邦国家采购商
A9: AUD | B9: 4.8 | C9: A$ | D9: 基准锁定汇率 (波动±3%保护) | E9: 澳大利亚、新西兰及大洋洲采购商
A10: CAD | B10: 5.3 | C10: C$ | D10: 基准锁定汇率 (波动±3%保护) | E10: 加拿大市场专属采购商
A12: 📈 模块二：利润红线与防穿底控制 (Profit Margin & Cost Protection)
A13: 参数控制项 (Control Parameter) | B13: 设置基准值 (Setting Value) | C13: 参数格式/单位 | D13: 系统生效机制与风控规则说明 | E13: 责任人/控制级别
A14: 全厂默认保底毛利率 (Default Margin) | B14: 0.15 | C14: 百分比 (0.15) | D14: 出厂安全底价基础上浮动加价；单品未设时自动继承此参数 | E14: 企业掌门人 / 老板
A15: 最低保护红线毛利率 (Floor Margin) | B15: 0.08 | C15: 百分比 (0.08) | D15: 业务员最低授权底线，低于此红线系统强制拦截并报警打回 | E15: 老板 / 财务总监
A16: 样品打样费上浮倍率 (Sample Multiplier) | B16: 2.5 | C16: 倍率 (出厂价*2.5) | D16: 覆盖小批量散单模具调机成本，后续批量达标全额抵扣货款 | E16: 厂长 / 工程部
A17: 报价单默认有效期 (Price Validity) | B17: 30 Days | C17: 天数 | D17: 超出 30 天需重新核实原材料成本与外币汇率波动情况 | E17: 外贸部主管
A19: 🚢 模块三：默认贸易术语与杂费基准 (Incoterms & Port Charges)
A20: 贸易术语 (Incoterm) | B20: 指定交货港口 / 地点 | C20: 单件均摊杂费 (RMB) | D20: 整柜固定杂费 (RMB) | E20: 费用包含范围与口岸说明
A21: EXW | B21: 工厂车间自提 (Factory Ex-works) | C21: 0 | D21: 0 | E21: 买家自提，仅含标准纸箱包装，无港口杂费与拖车费
A22: FOB | B22: 深圳盐田港 / 蛇口港 (Shenzhen) | C22: 0.2 | D22: 1500 | E22: 包含工厂至深圳码头内陆拖车、出口报关、港杂码头费(THC)
A23: CIF | B23: 目的港（根据买家询盘实时测算） | C23: 实时测算 | D23: 含基础货运险 | E23: 根据货柜实际目的港与实时船期核算海运费与保费
A25: 💳 模块四：默认付款方式与结算浮动 (Payment Terms)
A26: 付款方式 (Payment Term) | B26: 价格浮动比例 (%) | C26: 支持结算币种 | D26: 资金周转成本与商业规则说明 | E26: 适用客户等级与授信
A27: 100% T/T Advance (全款预付) | B27: -0.02 | C27: USD / EUR / GBP | D27: 买家全款预付直享 98 折，极大加速工厂现金流周转 | E27: 新老客户通用优惠
A28: 30% Deposit + 70% Balance (标准前T/T) | B28: 0 | C28: USD / EUR / GBP | D28: 外贸行业标准条款：30%定金排产，70%见提单副本付款 | E28: 标准成交客户
A29: L/C at Sight (即期不可撤销信用证) | B29: 0.015 | C29: USD / EUR | D29: 覆盖银行开证手续费与议付审单合规成本 | E29: 信用优良大客户
A31: 📦 模块五：集装箱装载容积速查标尺 (Container Volume Guidelines)
A32: 集装箱型号 (Container Type) | B32: 安全装载容积 (CBM) | C32: 理论容积 (CBM) | D32: 最大限重 (KG) | E32: 装柜适用选型建议
A33: 20GP (20尺小柜) | B33: 28 | C33: 33.2 | D33: 21800 | E33: 适合五金紧固件、金属椅脚等高密度重货或试单
A34: 40GP (40尺平柜) | B34: 58 | C34: 67.7 | D34: 26000 | E34: 适合体积适中、重量适中的常规工业品与配件
A35: 40HQ (40尺高柜) | B35: 68 | C35: 76.3 | D35: 26000 | E35: 适合办公椅、支架、轻泡货等大体积外贸商品

Sheet 📦 商品出厂底价库 (Products)
A1: 产品型号 / SKU (必填) | B1: 买家常用别名 (Aliases·选填) | C1: 产品英文品名与规格描述 (必填) | D1: 出厂底价 (RMB Cost·必填安全底价) | E1: 最低起订量 MOQ (PCS·选填) | F1: 单箱装量 (PCS/CTN·选填) | G1: 外箱体积 (CBM/CTN·选填) | H1: 单箱毛重 G.W. (kg/CTN·选填) | I1: 单品专属保底毛利率 (选填·留空继承15%) | J1: 专属生产交期 (选填·留空继承25-30天) | K1: 海关编码 HS Code (选填) | L1: ⚡ 单件港杂平摊(RMB) | M1: ⚡ 生效核算毛利率 | N1: 🎯 FOB美金单价(USD) | O1: 📦 20GP小柜装量(PCS) | P1: 📦 40HQ高柜装量(PCS) | Q1: 🛡️ 利润安全状态
A2: ST-2026-A | B2: ACME-991, Heavy Bracket, 991支架, Stand Pro | C2: Aluminum Alloy Precision Bracket (铝合金精密五金支架) | D2: 15.5 | E2: 500 | F2: 50 | G2: 0.045 | H2: 14.5 | J2: 20-25 Days | K2: 7616.99.9000 | L2: ='⚙️ 全局核算参数 (Config)'!$C$22 | M2: =IF(ISBLANK(I2), '⚙️ 全局核算参数 (Config)'!$B$14, I2) | N2: =ROUND(((D2 * (1 + M2) + L2) / '⚙️ 全局核算参数 (Config)'!$B$6), 2) | O2: =IF(AND(G2>0, F2>0), INT(('⚙️ 全局核算参数 (Config)'!$B$33 / G2)) * F2, "-") | P2: =IF(AND(G2>0, F2>0), INT(('⚙️ 全局核算参数 (Config)'!$B$35 / G2)) * F2, "-") | Q2: =IF(M2<'⚙️ 全局核算参数 (Config)'!$B$15, "🚨 穿透红线", IF(M2>=0.25, "💎 高毛利款", "✅ 利润健康"))
A3: ST-2026-B | B3: FAST-SCREW, Hex Bolt, 不锈钢紧固件, 8820螺丝 | C3: Stainless Steel Hex Fastener Screws (不锈钢沉头紧固件螺丝) | D3: 0.85 | E3: 5000 | F3: 1000 | G3: 0.02 | H3: 18 | I3: 0.18 | J3: 15-20 Days | K3: 7318.15.9000 | L3: ='⚙️ 全局核算参数 (Config)'!$C$22 | M3: =IF(ISBLANK(I3), '⚙️ 全局核算参数 (Config)'!$B$14, I3) | N3: =ROUND(((D3 * (1 + M3) + L3) / '⚙️ 全局核算参数 (Config)'!$B$6), 2) | O3: =IF(AND(G3>0, F3>0), INT(('⚙️ 全局核算参数 (Config)'!$B$33 / G3)) * F3, "-") | P3: =IF(AND(G3>0, F3>0), INT(('⚙️ 全局核算参数 (Config)'!$B$35 / G3)) * F3, "-") | Q3: =IF(M3<'⚙️ 全局核算参数 (Config)'!$B$15, "🚨 穿透红线", IF(M3>=0.25, "💎 高毛利款", "✅ 利润健康"))
A4: ERG-PRO-V2 | B4: Executive Chair, 9088办公椅, CHAIR-MESH-PRO, Ergo Chair | C4: Ergonomic Mesh Office Chair (高档网布人体工学办公椅) | D4: 185 | E4: 50 | F4: 1 | G4: 0.16 | H4: 16.2 | I4: 0.25 | J4: 30-35 Days | K4: 9401.30.0000 | L4: ='⚙️ 全局核算参数 (Config)'!$C$22 | M4: =IF(ISBLANK(I4), '⚙️ 全局核算参数 (Config)'!$B$14, I4) | N4: =ROUND(((D4 * (1 + M4) + L4) / '⚙️ 全局核算参数 (Config)'!$B$6), 2) | O4: =IF(AND(G4>0, F4>0), INT(('⚙️ 全局核算参数 (Config)'!$B$33 / G4)) * F4, "-") | P4: =IF(AND(G4>0, F4>0), INT(('⚙️ 全局核算参数 (Config)'!$B$35 / G4)) * F4, "-") | Q4: =IF(M4<'⚙️ 全局核算参数 (Config)'!$B$15, "🚨 穿透红线", IF(M4>=0.25, "💎 高毛利款", "✅ 利润健康"))
A5: AL-BASE-99 | B5: 5 Star Base, Chair Leg, 铝合金五星脚, Star Base 99 | C5: Die-casting Aluminum 5-Star Base (高压铸铝合金五星椅脚) | D5: 38 | E5: 200 | F5: 5 | G5: 0.08 | H5: 11 | J5: 25-30 Days | K5: 9401.90.9000 | L5: ='⚙️ 全局核算参数 (Config)'!$C$22 | M5: =IF(ISBLANK(I5), '⚙️ 全局核算参数 (Config)'!$B$14, I5) | N5: =ROUND(((D5 * (1 + M5) + L5) / '⚙️ 全局核算参数 (Config)'!$B$6), 2) | O5: =IF(AND(G5>0, F5>0), INT(('⚙️ 全局核算参数 (Config)'!$B$33 / G5)) * F5, "-") | P5: =IF(AND(G5>0, F5>0), INT(('⚙️ 全局核算参数 (Config)'!$B$35 / G5)) * F5, "-") | Q5: =IF(M5<'⚙️ 全局核算参数 (Config)'!$B$15, "🚨 穿透红线", IF(M5>=0.25, "💎 高毛利款", "✅ 利润健康"))
A6: HD-ARM-08 | B6: 3D Armrest, PU Arm, 升降扶手, ARM-08 | C6: 3D Adjustable PU Armrest Set (3D多功能升降PU扶手套装) | D6: 24 | E6: 300 | F6: 20 | G6: 0.055 | H6: 9.5 | J6: 20-25 Days | K6: 9401.90.9000 | L6: ='⚙️ 全局核算参数 (Config)'!$C$22 | M6: =IF(ISBLANK(I6), '⚙️ 全局核算参数 (Config)'!$B$14, I6) | N6: =ROUND(((D6 * (1 + M6) + L6) / '⚙️ 全局核算参数 (Config)'!$B$6), 2) | O6: =IF(AND(G6>0, F6>0), INT(('⚙️ 全局核算参数 (Config)'!$B$33 / G6)) * F6, "-") | P6: =IF(AND(G6>0, F6>0), INT(('⚙️ 全局核算参数 (Config)'!$B$35 / G6)) * F6, "-") | Q6: =IF(M6<'⚙️ 全局核算参数 (Config)'!$B$15, "🚨 穿透红线", IF(M6>=0.25, "💎 高毛利款", "✅ 利润健康"))
A7: HD-ARM-09 | B7: 3D Armrest Pro, PU Armrest Plus, 加强升降扶手, ARM-09 | C7: 3D Adjustable PU Armrest Set (3D多功能升降PU扶手套装) | D7: 25 | E7: 300 | F7: 20 | G7: 0.055 | H7: 9.5 | J7: 20-25 Days | K7: 9401.90.9000 | L7: ='⚙️ 全局核算参数 (Config)'!$C$22 | M7: =IF(ISBLANK(I7), '⚙️ 全局核算参数 (Config)'!$B$14, I7) | N7: =ROUND(((D7 * (1 + M7) + L7) / '⚙️ 全局核算参数 (Config)'!$B$6), 2) | O7: =IF(AND(G7>0, F7>0), INT(('⚙️ 全局核算参数 (Config)'!$B$33 / G7)) * F7, "-") | P7: =IF(AND(G7>0, F7>0), INT(('⚙️ 全局核算参数 (Config)'!$B$35 / G7)) * F7, "-") | Q7: =IF(M7<'⚙️ 全局核算参数 (Config)'!$B$15, "🚨 穿透红线", IF(M7>=0.25, "💎 高毛利款", "✅ 利润健康"))

Sheet 📄 对外纯净批量报价单 (脱敏单)
A1: GLOBAL EXPORT FORMAL QUOTATION (COMMERCIAL OFFER)
A2: Trade Term: FOB Shenzhen (Incoterms 2020) | Currency: USD ($) | F2: Payment: 30% Deposit, 70% Before Shipment | Price Validity: 30 Days
A3: Item | B3: Model No. | C3: Product Description & Detailed Specifications | D3: MOQ (PCS) | E3: FOB Price (USD) | F3: Packing (PCS/CTN) | G3: 20GP Est. (PCS) | H3: 40HQ Est. (PCS) | I3: Lead Time
A4: 1 | B4: ='📦 商品出厂底价库 (Products)'!A2 | C4: ='📦 商品出厂底价库 (Products)'!C2 | D4: ='📦 商品出厂底价库 (Products)'!E2 | E4: ='📦 商品出厂底价库 (Products)'!N2 | F4: ='📦 商品出厂底价库 (Products)'!F2 | G4: ='📦 商品出厂底价库 (Products)'!O2 | H4: ='📦 商品出厂底价库 (Products)'!P2 | I4: ='📦 商品出厂底价库 (Products)'!J2
A5: 2 | B5: ='📦 商品出厂底价库 (Products)'!A3 | C5: ='📦 商品出厂底价库 (Products)'!C3 | D5: ='📦 商品出厂底价库 (Products)'!E3 | E5: ='📦 商品出厂底价库 (Products)'!N3 | F5: ='📦 商品出厂底价库 (Products)'!F3 | G5: ='📦 商品出厂底价库 (Products)'!O3 | H5: ='📦 商品出厂底价库 (Products)'!P3 | I5: ='📦 商品出厂底价库 (Products)'!J3
A6: 3 | B6: ='📦 商品出厂底价库 (Products)'!A4 | C6: ='📦 商品出厂底价库 (Products)'!C4 | D6: ='📦 商品出厂底价库 (Products)'!E4 | E6: ='📦 商品出厂底价库 (Products)'!N4 | F6: ='📦 商品出厂底价库 (Products)'!F4 | G6: ='📦 商品出厂底价库 (Products)'!O4 | H6: ='📦 商品出厂底价库 (Products)'!P4 | I6: ='📦 商品出厂底价库 (Products)'!J4
A7: 4 | B7: ='📦 商品出厂底价库 (Products)'!A5 | C7: ='📦 商品出厂底价库 (Products)'!C5 | D7: ='📦 商品出厂底价库 (Products)'!E5 | E7: ='📦 商品出厂底价库 (Products)'!N5 | F7: ='📦 商品出厂底价库 (Products)'!F5 | G7: ='📦 商品出厂底价库 (Products)'!O5 | H7: ='📦 商品出厂底价库 (Products)'!P5 | I7: ='📦 商品出厂底价库 (Products)'!J5
A8: 5 | B8: ='📦 商品出厂底价库 (Products)'!A6 | C8: ='📦 商品出厂底价库 (Products)'!C6 | D8: ='📦 商品出厂底价库 (Products)'!E6 | E8: ='📦 商品出厂底价库 (Products)'!N6 | F8: ='📦 商品出厂底价库 (Products)'!F6 | G8: ='📦 商品出厂底价库 (Products)'!O6 | H8: ='📦 商品出厂底价库 (Products)'!P6 | I8: ='📦 商品出厂底价库 (Products)'!J6
A9: 6 | B9: ='📦 商品出厂底价库 (Products)'!A7 | C9: ='📦 商品出厂底价库 (Products)'!C7 | D9: ='📦 商品出厂底价库 (Products)'!E7 | E9: ='📦 商品出厂底价库 (Products)'!N7 | F9: ='📦 商品出厂底价库 (Products)'!F7 | G9: ='📦 商品出厂底价库 (Products)'!O7 | H9: ='📦 商品出厂底价库 (Products)'!P7 | I9: ='📦 商品出厂底价库 (Products)'!J7
